mtfor/__init__.py
mtfor-0.0.4.dist-info/LICENSE
mtfor-0.0.4.dist-info/METADATA
mtfor-0.0.4.dist-info/WHEEL
mtfor-0.0.4.dist-info/top_level.txt
mtfor-0.0.4.dist-info/RECORD
