Metadata-Version: 2.1
Name: mtfor
Version: 0.0.4
Summary: Plug 'n' play multithreaded for
Home-page: https://github.com/solanav/mtfor
Author: Antonio Solana
Author-email: solanav@qq.com
License: UNKNOWN
Platform: UNKNOWN
Classifier: Programming Language :: Python :: 3
Classifier: License :: OSI Approved :: GNU General Public License v3 (GPLv3)
Classifier: Operating System :: OS Independent
Requires-Python: >=3.6
